cookiecutter_pdm-0.0.3.dist-info/METADATA
cookiecutter_pdm-0.0.3.dist-info/WHEEL
cookiecutter_pdm-0.0.3.dist-info/entry_points.txt
cookiecutter_pdm-0.0.3.dist-info/licenses/LICENSE
cookiecutter_pdm/__init__.py
cookiecutter_pdm/cli.py
cookiecutter_pdm-0.0.3.dist-info/RECORD
