Metadata-Version: 2.1
Name: cookiecutter-pdm
Version: 0.0.3
Summary: A python cookiecutter application to create a new python project that uses PDM to manage its dependencies.
Keywords: cookiecutter template PDM
Author-Email: Florian Maas <info@fpgmaas.com>
License: MIT
Project-URL: Repository, https://github.com/fpgmaas/cookiecutter-pdm
Project-URL: Documentation, https://fpgmaas.github.io/cookiecutter-pdm/
Project-URL: Homepage, https://fpgmaas.github.io/cookiecutter-pdm/
Requires-Python: <4.0,>=3.8
Requires-Dist: cookiecutter>=2.1.1
